clickhouse_connect/VERSION
clickhouse_connect/__init__.py
clickhouse_connect/common.py
clickhouse_connect/entry_points.py
clickhouse_connect/json_impl.py
clickhouse_connect/cc_sqlalchemy/__init__.py
clickhouse_connect/cc_sqlalchemy/dialect.py
clickhouse_connect/cc_sqlalchemy/inspector.py
clickhouse_connect/cc_sqlalchemy/datatypes/__init__.py
clickhouse_connect/cc_sqlalchemy/datatypes/base.py
clickhouse_connect/cc_sqlalchemy/datatypes/sqltypes.py
clickhouse_connect/cc_sqlalchemy/ddl/__init__.py
clickhouse_connect/cc_sqlalchemy/ddl/custom.py
clickhouse_connect/cc_sqlalchemy/ddl/tableengine.py
clickhouse_connect/cc_sqlalchemy/sql/__init__.py
clickhouse_connect/cc_sqlalchemy/sql/ddlcompiler.py
clickhouse_connect/cc_sqlalchemy/sql/preparer.py
clickhouse_connect/cc_superset/__init__.py
clickhouse_connect/cc_superset/datatypes.py
clickhouse_connect/cc_superset/engine.py
clickhouse_connect/datatypes/__init__.py
clickhouse_connect/datatypes/base.py
clickhouse_connect/datatypes/container.py
clickhouse_connect/datatypes/format.py
clickhouse_connect/datatypes/network.py
clickhouse_connect/datatypes/numeric.py
clickhouse_connect/datatypes/registry.py
clickhouse_connect/datatypes/special.py
clickhouse_connect/datatypes/string.py
clickhouse_connect/datatypes/temporal.py
clickhouse_connect/dbapi/__init__.py
clickhouse_connect/dbapi/connection.py
clickhouse_connect/dbapi/cursor.py
clickhouse_connect/driver/__init__.py
clickhouse_connect/driver/buffer.py
clickhouse_connect/driver/client.py
clickhouse_connect/driver/common.py
clickhouse_connect/driver/compression.py
clickhouse_connect/driver/constants.py
clickhouse_connect/driver/context.py
clickhouse_connect/driver/ctypes.py
clickhouse_connect/driver/dataconv.py
clickhouse_connect/driver/ddl.py
clickhouse_connect/driver/exceptions.py
clickhouse_connect/driver/extras.py
clickhouse_connect/driver/httpclient.py
clickhouse_connect/driver/httputil.py
clickhouse_connect/driver/insert.py
clickhouse_connect/driver/models.py
clickhouse_connect_dengine-0.5.15.dist-info/LICENSE
clickhouse_connect_dengine-0.5.15.dist-info/METADATA
clickhouse_connect_dengine-0.5.15.dist-info/WHEEL
clickhouse_connect_dengine-0.5.15.dist-info/entry_points.txt
clickhouse_connect_dengine-0.5.15.dist-info/top_level.txt
clickhouse_connect_dengine-0.5.15.dist-info/RECORD
